MANIFEST.in
README.md
requirements.txt
setup.py
sbg_cwl_upgrader/__init__.py
sbg_cwl_upgrader/cwl_utils.py
sbg_cwl_upgrader/sbg_utils.py
sbg_cwl_upgrader/converter/__init__.py
sbg_cwl_upgrader/converter/connection_checker.py
sbg_cwl_upgrader/converter/cwl_converter.py
sbg_cwl_upgrader/converter/sbg_draft2_to_cwl_1_0.py
sbg_cwl_upgrader/converter/tool.py
sbg_cwl_upgrader/converter/workflow.py
sbg_cwl_upgrader/decomposer/__init__.py
sbg_cwl_upgrader/decomposer/local.py
sbg_cwl_upgrader/decomposer/remote.py
sbg_cwl_upgrader/decomposer/sbg_cwl_decomposer.py
sbg_cwl_upgrader/resources/expression_lib.js
sbg_cwl_upgrader/validator/__init__.py
sbg_cwl_upgrader/validator/cwl_validation.py
sbg_cwl_upgrader/validator/sbg_validate_js_cwl_v1.py
sevenbridges_cwl_draft2_upgrader.egg-info/PKG-INFO
sevenbridges_cwl_draft2_upgrader.egg-info/SOURCES.txt
sevenbridges_cwl_draft2_upgrader.egg-info/dependency_links.txt
sevenbridges_cwl_draft2_upgrader.egg-info/entry_points.txt
sevenbridges_cwl_draft2_upgrader.egg-info/requires.txt
sevenbridges_cwl_draft2_upgrader.egg-info/top_level.txt
tests/__init__.py
tests/converter/__init__.py
tests/converter/test_connection_checker.py
tests/converter/test_cwl_converter.py
tests/converter/test_sbg_draft2_to_cwl1.py
tests/converter/test_tool.py
tests/converter/test_workflow.py
tests/decomposer/__init__.py
tests/decomposer/test_local.py
tests/decomposer/test_remote.py
tests/decomposer/test_sbg_cwl_decomposer.py
tests/utils/__init__.py
tests/utils/test_cwl_utils.py
tests/utils/test_sbg_utils.py
tests/validator/__init__.py
tests/validator/test_cwl_validation.py