Metadata-Version: 2.1
Name: sevenbridges-cwl-draft2-upgrader
Version: 0.3.0
Summary: Seven Bridges CWL sbg:draft2 to v1.0 upgrader.
Home-page: https://github.com/sbg/sevenbridges-cwl-draft2-upgrader
Maintainer: Seven Bridges Genomics Inc.
Maintainer-email: bogdan.gavrilovic@sbgenomics.com
License: Apache Software License 2.0
Keywords: sevenbridges,sbg,cwl
Platform: POSIX
Platform: MacOS
Classifier: Intended Audience :: Developers
Classifier: License :: OSI Approved :: Apache Software License
Classifier: Natural Language :: English
Classifier: Operating System :: POSIX
Classifier: Programming Language :: Python :: 3
Requires-Python: >=3.6.0
